tokybook-audiobook-fetcher/__init__.py
tokybook-audiobook-fetcher/download.py
tokybook-audiobook-fetcher/main.py
tokybook-audiobook-fetcher/scrape.py
tokybook_audiobook_fetcher/__init__.py
tokybook_audiobook_fetcher/download.py
tokybook_audiobook_fetcher/main.py
tokybook_audiobook_fetcher/scrape.py
tokybook_audiobook_fetcher-0.4.dist-info/METADATA
tokybook_audiobook_fetcher-0.4.dist-info/WHEEL
tokybook_audiobook_fetcher-0.4.dist-info/entry_points.txt
tokybook_audiobook_fetcher-0.4.dist-info/top_level.txt
tokybook_audiobook_fetcher-0.4.dist-info/RECORD
